readstore_cli/__init__.py
readstore_cli/__version__.py
readstore_cli/readstore.py
readstore_cli/rsclient.py
readstore_cli/rsconfig.py
readstore_cli/rsexceptions.py
readstore_cli-1.2.0.dist-info/LICENSE
readstore_cli-1.2.0.dist-info/METADATA
readstore_cli-1.2.0.dist-info/WHEEL
readstore_cli-1.2.0.dist-info/entry_points.txt
readstore_cli-1.2.0.dist-info/top_level.txt
readstore_cli-1.2.0.dist-info/RECORD
