Metadata-Version: 2.1
Name: readstore-cli
Version: 1.2.0
Summary: ReadStore Command Line Interface (CLI) Is A Python Package For Accessing Data from the ReadStore API
Home-page: https://github.com/EvobyteDigitalBiology/readstore-cli
Author: Jonathan Alles
Author-email: Jonathan.Alles@evo-byte.com
License: Apache-2.0 license
Classifier: Programming Language :: Python :: 3
Classifier: License :: OSI Approved :: Apache Software License
Classifier: Operating System :: Unix
Requires-Python: >=3.10
License-File: LICENSE
Requires-Dist: requests>=2.32.3
